<?xml version='1.0' encoding='utf-8'?><m:layout id='3ffe4fe7-abe9-4db7-8d74-aa32f8f9327d' xmlns='http://www.w3.org/1999/xhtml' xmlns:m='http://schemas.mendix.com/forms/1.0'><m:arguments><m:argument><div data-mendix-id='7.Atlas_Core.Tablet_FullPage.layoutContainer' data-mendix-type='mxui.widget.VerticalScrollContainer' data-mendix-props='"fixed":true,"config":[{"position":"middle"}]' class='mx-scrollcontainer mx-scrollcontainer-vertical mx-scrollcontainer-fixed'><div class='mx-scrollcontainer-middle region-content'><div class='mx-scrollcontainer-wrapper'><div data-mx-placeholder='9154a384-9f0c-4fd1-9db8-b31c22105403' class='mx-placeholder'></div></div></div></div></m:argument></m:arguments></m:layout>